whisper_dictation/Client.py
whisper_dictation/DictationDeamon.py
whisper_dictation/WhisperDictator.py
whisper_dictation/__init__.py
whisper_dictation/cli.py
whisper_dictation/whisper_dictation.service
whisper_dictation-0.4.3.dist-info/LICENSE
whisper_dictation-0.4.3.dist-info/METADATA
whisper_dictation-0.4.3.dist-info/WHEEL
whisper_dictation-0.4.3.dist-info/entry_points.txt
whisper_dictation-0.4.3.dist-info/RECORD
