Metadata-Version: 2.1
Name: whisper-dictation
Version: 0.4.3
Summary: 
Author: Lumen Young
Author-email: lumen.young@lumeny.io
Requires-Python: >=3.10,<4.0
Classifier: Programming Language :: Python :: 3
Classifier: Programming Language :: Python :: 3.10
Classifier: Programming Language :: Python :: 3.11
Requires-Dist: click (>=8.1.3,<9.0.0)
Requires-Dist: openai-whisper (>=20230314,<20230315)
Requires-Dist: pyaudio (>=0.2.13,<0.3.0)
